gtfs_kit/__init__.py
gtfs_kit/calendar.py
gtfs_kit/cleaners.py
gtfs_kit/constants.py
gtfs_kit/feed.py
gtfs_kit/helpers.py
gtfs_kit/miscellany.py
gtfs_kit/routes.py
gtfs_kit/shapes.py
gtfs_kit/stop_times.py
gtfs_kit/stops.py
gtfs_kit/trips.py
gtfs_kit-12.0.0.dist-info/METADATA
gtfs_kit-12.0.0.dist-info/WHEEL
gtfs_kit-12.0.0.dist-info/licenses/LICENSE.txt
gtfs_kit-12.0.0.dist-info/RECORD
