Metadata-Version: 2.4
Name: gtfs-kit
Version: 12.0.0
Summary: A Python library for analyzing GTFS feeds.
Project-URL: Repository, https://github.com/mrcagney/gtfs_kit
Project-URL: Documentation, https://mrcagney.github.io/gtfs_kit_docs
Author-email: Alexander Raichev <araichev@mrcagney.com>
License-Expression: MIT
License-File: LICENSE.txt
Requires-Python: >=3.10
Requires-Dist: folium>=0
Requires-Dist: geopandas>=1
Requires-Dist: json2html>=1
Requires-Dist: pandas>=2.2.2
Requires-Dist: requests>=2
Requires-Dist: rtree>=0
Requires-Dist: shapely>=1.8
